ovos_plugin_qt5/__init__.py
ovos_plugin_qt5/version.py
ovos_plugin_qt5/qt5/AudioPlayerControl.qml
ovos_plugin_qt5/qt5/GenericCloseControl.qml
ovos_plugin_qt5/qt5/OVOSAudioPlayer.qml
ovos_plugin_qt5/qt5/OVOSSeekControl.qml
ovos_plugin_qt5/qt5/OVOSVideoPlayer.qml
ovos_plugin_qt5/qt5/OVOSWebPlayer.qml
ovos_plugin_qt5/qt5/SpectrumWaveDelegate.qml
ovos_plugin_qt5/qt5/VideoPlayerControl.qml
ovos_plugin_qt5/qt5/code/helper.js
ovos_plugin_qt5/qt5/code/nav.js
ovos_plugin_qt5/qt5/images/liked.svg
ovos_plugin_qt5/qt5/images/media-playback-pause.svg
ovos_plugin_qt5/qt5/images/media-playback-start.svg
ovos_plugin_qt5/qt5/images/media-playback-stop.svg
ovos_plugin_qt5/qt5/images/media-playlist-play.svg
ovos_plugin_qt5/qt5/images/media-playlist-repeat-track.svg
ovos_plugin_qt5/qt5/images/media-playlist-repeat.svg
ovos_plugin_qt5/qt5/images/media-playlist-shuffle.svg
ovos_plugin_qt5/qt5/images/media-skip-backward.svg
ovos_plugin_qt5/qt5/images/media-skip-forward.svg
ovos_media_plugin_qt5-0.1.0a2.dist-info/LICENSE
ovos_media_plugin_qt5-0.1.0a2.dist-info/METADATA
ovos_media_plugin_qt5-0.1.0a2.dist-info/WHEEL
ovos_media_plugin_qt5-0.1.0a2.dist-info/entry_points.txt
ovos_media_plugin_qt5-0.1.0a2.dist-info/top_level.txt
ovos_media_plugin_qt5-0.1.0a2.dist-info/RECORD
